oscovida/__init__.py
oscovida/data_sources.py
oscovida/metadata.py
oscovida/oscovida.py
oscovida/plotting_helpers.py
oscovida-0.2.6.dist-info/LICENSE
oscovida-0.2.6.dist-info/METADATA
oscovida-0.2.6.dist-info/WHEEL
oscovida-0.2.6.dist-info/top_level.txt
oscovida-0.2.6.dist-info/RECORD
