Metadata-Version: 2.1
Name: oscovida
Version: 0.2.6
Summary: Coronavirus-2020
Home-page: https://github.com/oscovida/oscovida
Author: European XFEL GmbH
Author-email: da-support@xfel.eu
Maintainer: Hans Fangohr
License: BSD-3-Clause
Platform: UNKNOWN
Classifier: Intended Audience :: Developers
Classifier: Intended Audience :: Science/Research
Classifier: License :: OSI Approved :: BSD License
Classifier: Operating System :: POSIX :: Linux
Classifier: Programming Language :: Python :: 3
Classifier: Topic :: Scientific/Engineering :: Information Analysis
Requires-Python: >=3.6
Requires-Dist: joblib
Requires-Dist: pandas
Requires-Dist: seaborn
Requires-Dist: matplotlib
Requires-Dist: markdown
Requires-Dist: openpyxl
Requires-Dist: numpy
Requires-Dist: scipy
Requires-Dist: voila
Requires-Dist: pelican
Requires-Dist: pelican-jupyter
Requires-Dist: tabulate (<0.8.8)
Requires-Dist: tqdm
Requires-Dist: ipywidgets
Requires-Dist: ipynb-py-convert
Requires-Dist: click
Requires-Dist: pytest-tornasync
Requires-Dist: nbconvert (==6.0.1)
Requires-Dist: plotly
Provides-Extra: test
Requires-Dist: pytest ; extra == 'test'
Requires-Dist: pytest-cov ; extra == 'test'
Requires-Dist: coverage ; extra == 'test'
Requires-Dist: nbval ; extra == 'test'
Requires-Dist: testpath ; extra == 'test'
Requires-Dist: pycodestyle ; extra == 'test'
